selenium_wrapper_3/__init__.py
selenium_wrapper_3/__main__.py
selenium_wrapper_3/_xpath_parser/__init__.py
selenium_wrapper_3/_xpath_parser/args_parser.py
selenium_wrapper_3/_xpath_parser/sw3_parser.py
selenium_wrapper_3/_xpath_parser/xpath_parser.py
selenium_wrapper_3/builder/__init__.py
selenium_wrapper_3/builder/builder.py
selenium_wrapper_3/driver/__init__.py
selenium_wrapper_3/driver/driver.py
selenium_wrapper_3/exception/__init__.py
selenium_wrapper_3/exception/exception.py
selenium_wrapper_3/node/__init__.py
selenium_wrapper_3/node/node.py
selenium_wrapper_3/pattern/__init__.py
selenium_wrapper_3/pattern/lazy_import.py
selenium_wrapper_3/pattern/singleton.py
selenium_wrapper_3/util/__init__.py
selenium_wrapper_3/util/util.py
Selenium_Wrapper_3-1.2.3.dist-info/METADATA
Selenium_Wrapper_3-1.2.3.dist-info/WHEEL
Selenium_Wrapper_3-1.2.3.dist-info/entry_points.txt
Selenium_Wrapper_3-1.2.3.dist-info/top_level.txt
Selenium_Wrapper_3-1.2.3.dist-info/RECORD
