Metadata-Version: 2.1
Name: Selenium-Wrapper-3
Version: 1.2.3
Summary: Selenium Wrapper 3
Author: Sunwoo Kim
Author-email: sunshower1127@gmail.com
Keywords: selenium,wrapper,webdriver,python,selenium-wrapper
Requires-Python: >=3.9
Requires-Dist: selenium
Requires-Dist: pyperclip
